pygba/__init__.py
pygba/gym_env.py
pygba/pygba.py
pygba/utils.py
pygba/game_wrappers/base.py
pygba/game_wrappers/pokemon_emerald.py
pygba/game_wrappers/utils/emerald_utils.py
pygba-0.2.9.dist-info/LICENSE
pygba-0.2.9.dist-info/METADATA
pygba-0.2.9.dist-info/WHEEL
pygba-0.2.9.dist-info/top_level.txt
pygba-0.2.9.dist-info/RECORD
