Metadata-Version: 2.1
Name: pygba
Version: 0.2.9
Summary: A Python wrapper around the Game Boy Advance emulator mGBA with built-in support for gymnasium environments.
Author: Dimitri von Rütte
License: MIT
Project-URL: github, https://github.com/dvruette/pygba
Keywords: gba,mgba,emulator,gymnasium,reinforcement-learning
Classifier: License :: OSI Approved :: MIT License
Classifier: Programming Language :: Python :: 3
Classifier: Topic :: Software Development :: Libraries
License-File: LICENSE
Requires-Dist: gymnasium
Requires-Dist: numpy
Requires-Dist: pygame
Requires-Dist: mgba ; platform_system == "Linux" or platform_system == "Darwin"
